ifreq.cpython-39-x86_64-linux-gnu.so
ifreq.pyi
ifreq-0.2.0.dist-info/LICENSE
ifreq-0.2.0.dist-info/WHEEL
ifreq-0.2.0.dist-info/RECORD
ifreq-0.2.0.dist-info/METADATA
ifreq-0.2.0.dist-info/top_level.txt
