Metadata-Version: 2.1
Name: ifreq
Version: 0.2.0
Summary: Control Network Interface In Object Oriented Method
Author: skrab-sah
Author-email: skrab.sah@gmail.com
Classifier: Operating System :: POSIX :: Linux
Classifier: License :: OSI Approved :: MIT License
License-File: LICENSE
